{
    "latent-model": false,
    "name": "m586",
    "variables": [
        {
            "determination": {
                "table": [
                    [
                        "qmg",
                        [
                            "fzs",
                            "jju"
                        ],
                        0.046
                    ],
                    [
                        "~qmg",
                        [
                            "fzs",
                            "jju"
                        ],
                        0.954
                    ],
                    [
                        "qmg",
                        [
                            "fzs",
                            "~jju"
                        ],
                        0.0376
                    ],
                    [
                        "~qmg",
                        [
                            "fzs",
                            "~jju"
                        ],
                        0.9624
                    ],
                    [
                        "qmg",
                        [
                            "~fzs",
                            "jju"
                        ],
                        0.2102
                    ],
                    [
                        "~qmg",
                        [
                            "~fzs",
                            "jju"
                        ],
                        0.7898
                    ],
                    [
                        "qmg",
                        [
                            "~fzs",
                            "~jju"
                        ],
                        0.464
                    ],
                    [
                        "~qmg",
                        [
                            "~fzs",
                            "~jju"
                        ],
                        0.536
                    ]
                ],
                "type": "table"
            },
            "name": "QMG",
            "outcomes": [
                "qmg",
                "~qmg"
            ],
            "parents": [
                "FZS",
                "JJU"
            ]
        },
        {
            "determination": {
                "table": [
                    [
                        "xut",
                        [
                            "fzs",
                            "hyy",
                            "qmg"
                        ],
                        0.7404
                    ],
                    [
                        "~xut",
                        [
                            "fzs",
                            "hyy",
                            "qmg"
                        ],
                        0.2596
                    ],
                    [
                        "xut",
                        [
                            "fzs",
                            "hyy",
                            "~qmg"
                        ],
                        0.977
                    ],
                    [
                        "~xut",
                        [
                            "fzs",
                            "hyy",
                            "~qmg"
                        ],
                        0.023
                    ],
                    [
                        "xut",
                        [
                            "fzs",
                            "~hyy",
                            "qmg"
                        ],
                        0.3301
                    ],
                    [
                        "~xut",
                        [
                            "fzs",
                            "~hyy",
                            "qmg"
                        ],
                        0.6699
                    ],
                    [
                        "xut",
                        [
                            "fzs",
                            "~hyy",
                            "~qmg"
                        ],
                        0.5775
                    ],
                    [
                        "~xut",
                        [
                            "fzs",
                            "~hyy",
                            "~qmg"
                        ],
                        0.4225
                    ],
                    [
                        "xut",
                        [
                            "~fzs",
                            "hyy",
                            "qmg"
                        ],
                        0.6673
                    ],
                    [
                        "~xut",
                        [
                            "~fzs",
                            "hyy",
                            "qmg"
                        ],
                        0.3327
                    ],
                    [
                        "xut",
                        [
                            "~fzs",
                            "hyy",
                            "~qmg"
                        ],
                        0.602
                    ],
                    [
                        "~xut",
                        [
                            "~fzs",
                            "hyy",
                            "~qmg"
                        ],
                        0.398
                    ],
                    [
                        "xut",
                        [
                            "~fzs",
                            "~hyy",
                            "qmg"
                        ],
                        0.7766
                    ],
                    [
                        "~xut",
                        [
                            "~fzs",
                            "~hyy",
                            "qmg"
                        ],
                        0.2234
                    ],
                    [
                        "xut",
                        [
                            "~fzs",
                            "~hyy",
                            "~qmg"
                        ],
                        0.8113
                    ],
                    [
                        "~xut",
                        [
                            "~fzs",
                            "~hyy",
                            "~qmg"
                        ],
                        0.1887
                    ]
                ],
                "type": "table"
            },
            "name": "XUT",
            "outcomes": [
                "xut",
                "~xut"
            ],
            "parents": [
                "FZS",
                "HYY",
                "QMG"
            ]
        },
        {
            "determination": {
                "table": [
                    [
                        "fzs",
                        [],
                        0.1881
                    ],
                    [
                        "~fzs",
                        [],
                        0.8119
                    ]
                ],
                "type": "table"
            },
            "name": "FZS",
            "outcomes": [
                "fzs",
                "~fzs"
            ],
            "parents": []
        },
        {
            "determination": {
                "table": [
                    [
                        "hyy",
                        [
                            "fzs",
                            "jju"
                        ],
                        0.6205
                    ],
                    [
                        "~hyy",
                        [
                            "fzs",
                            "jju"
                        ],
                        0.3795
                    ],
                    [
                        "hyy",
                        [
                            "fzs",
                            "~jju"
                        ],
                        0.8705
                    ],
                    [
                        "~hyy",
                        [
                            "fzs",
                            "~jju"
                        ],
                        0.1295
                    ],
                    [
                        "hyy",
                        [
                            "~fzs",
                            "jju"
                        ],
                        0.2552
                    ],
                    [
                        "~hyy",
                        [
                            "~fzs",
                            "jju"
                        ],
                        0.7448
                    ],
                    [
                        "hyy",
                        [
                            "~fzs",
                            "~jju"
                        ],
                        0.1123
                    ],
                    [
                        "~hyy",
                        [
                            "~fzs",
                            "~jju"
                        ],
                        0.8877
                    ]
                ],
                "type": "table"
            },
            "name": "HYY",
            "outcomes": [
                "hyy",
                "~hyy"
            ],
            "parents": [
                "FZS",
                "JJU"
            ]
        },
        {
            "determination": {
                "table": [
                    [
                        "tui",
                        [
                            "fzs",
                            "hyy",
                            "jju",
                            "qmg"
                        ],
                        0.3738
                    ],
                    [
                        "~tui",
                        [
                            "fzs",
                            "hyy",
                            "jju",
                            "qmg"
                        ],
                        0.6262
                    ],
                    [
                        "tui",
                        [
                            "fzs",
                            "hyy",
                            "jju",
                            "~qmg"
                        ],
                        0.8726
                    ],
                    [
                        "~tui",
                        [
                            "fzs",
                            "hyy",
                            "jju",
                            "~qmg"
                        ],
                        0.1274
                    ],
                    [
                        "tui",
                        [
                            "fzs",
                            "hyy",
                            "~jju",
                            "qmg"
                        ],
                        0.5574
                    ],
                    [
                        "~tui",
                        [
                            "fzs",
                            "hyy",
                            "~jju",
                            "qmg"
                        ],
                        0.4426
                    ],
                    [
                        "tui",
                        [
                            "fzs",
                            "hyy",
                            "~jju",
                            "~qmg"
                        ],
                        0.7935
                    ],
                    [
                        "~tui",
                        [
                            "fzs",
                            "hyy",
                            "~jju",
                            "~qmg"
                        ],
                        0.2065
                    ],
                    [
                        "tui",
                        [
                            "fzs",
                            "~hyy",
                            "jju",
                            "qmg"
                        ],
                        0.4127
                    ],
                    [
                        "~tui",
                        [
                            "fzs",
                            "~hyy",
                            "jju",
                            "qmg"
                        ],
                        0.5873
                    ],
                    [
                        "tui",
                        [
                            "fzs",
                            "~hyy",
                            "jju",
                            "~qmg"
                        ],
                        0.1502
                    ],
                    [
                        "~tui",
                        [
                            "fzs",
                            "~hyy",
                            "jju",
                            "~qmg"
                        ],
                        0.8498
                    ],
                    [
                        "tui",
                        [
                            "fzs",
                            "~hyy",
                            "~jju",
                            "qmg"
                        ],
                        0.0006
                    ],
                    [
                        "~tui",
                        [
                            "fzs",
                            "~hyy",
                            "~jju",
                            "qmg"
                        ],
                        0.9994
                    ],
                    [
                        "tui",
                        [
                            "fzs",
                            "~hyy",
                            "~jju",
                            "~qmg"
                        ],
                        0.9608
                    ],
                    [
                        "~tui",
                        [
                            "fzs",
                            "~hyy",
                            "~jju",
                            "~qmg"
                        ],
                        0.0392
                    ],
                    [
                        "tui",
                        [
                            "~fzs",
                            "hyy",
                            "jju",
                            "qmg"
                        ],
                        0.1292
                    ],
                    [
                        "~tui",
                        [
                            "~fzs",
                            "hyy",
                            "jju",
                            "qmg"
                        ],
                        0.8708
                    ],
                    [
                        "tui",
                        [
                            "~fzs",
                            "hyy",
                            "jju",
                            "~qmg"
                        ],
                        0.5587
                    ],
                    [
                        "~tui",
                        [
                            "~fzs",
                            "hyy",
                            "jju",
                            "~qmg"
                        ],
                        0.4413
                    ],
                    [
                        "tui",
                        [
                            "~fzs",
                            "hyy",
                            "~jju",
                            "qmg"
                        ],
                        0.9847
                    ],
                    [
                        "~tui",
                        [
                            "~fzs",
                            "hyy",
                            "~jju",
                            "qmg"
                        ],
                        0.0153
                    ],
                    [
                        "tui",
                        [
                            "~fzs",
                            "hyy",
                            "~jju",
                            "~qmg"
                        ],
                        0.3944
                    ],
                    [
                        "~tui",
                        [
                            "~fzs",
                            "hyy",
                            "~jju",
                            "~qmg"
                        ],
                        0.6056
                    ],
                    [
                        "tui",
                        [
                            "~fzs",
                            "~hyy",
                            "jju",
                            "qmg"
                        ],
                        0.0045
                    ],
                    [
                        "~tui",
                        [
                            "~fzs",
                            "~hyy",
                            "jju",
                            "qmg"
                        ],
                        0.9955
                    ],
                    [
                        "tui",
                        [
                            "~fzs",
                            "~hyy",
                            "jju",
                            "~qmg"
                        ],
                        0.7214
                    ],
                    [
                        "~tui",
                        [
                            "~fzs",
                            "~hyy",
                            "jju",
                            "~qmg"
                        ],
                        0.2786
                    ],
                    [
                        "tui",
                        [
                            "~fzs",
                            "~hyy",
                            "~jju",
                            "qmg"
                        ],
                        0.6979
                    ],
                    [
                        "~tui",
                        [
                            "~fzs",
                            "~hyy",
                            "~jju",
                            "qmg"
                        ],
                        0.3021
                    ],
                    [
                        "tui",
                        [
                            "~fzs",
                            "~hyy",
                            "~jju",
                            "~qmg"
                        ],
                        0.893
                    ],
                    [
                        "~tui",
                        [
                            "~fzs",
                            "~hyy",
                            "~jju",
                            "~qmg"
                        ],
                        0.107
                    ]
                ],
                "type": "table"
            },
            "name": "TUI",
            "outcomes": [
                "tui",
                "~tui"
            ],
            "parents": [
                "FZS",
                "HYY",
                "JJU",
                "QMG"
            ]
        },
        {
            "determination": {
                "table": [
                    [
                        "jju",
                        [],
                        0.1774
                    ],
                    [
                        "~jju",
                        [],
                        0.8226
                    ]
                ],
                "type": "table"
            },
            "name": "JJU",
            "outcomes": [
                "jju",
                "~jju"
            ],
            "parents": []
        }
    ]
}